muse_nanoleaf/Config.py
muse_nanoleaf/LightManager.py
muse_nanoleaf/LightMixer.py
muse_nanoleaf/MovingAverage.py
muse_nanoleaf/MuseState.py
muse_nanoleaf/StoppableThread.py
muse_nanoleaf/__init__.py
muse_nanoleaf/museServer.py
muse_nanoleaf/nanoleaf.py
muse_nanoleaf-0.0.1.dist-info/METADATA
muse_nanoleaf-0.0.1.dist-info/RECORD
muse_nanoleaf-0.0.1.dist-info/WHEEL
muse_nanoleaf-0.0.1.dist-info/top_level.txt
