Metadata-Version: 2.1
Name: muse-nanoleaf
Version: 0.0.1
Summary: A muse/nanoleaf integration
Home-page: https://github.com/LLay/muse_nanoleaf
Author: Lyon Lay
Author-email: lay.lyon@gmail.com
License: UNKNOWN
Platform: UNKNOWN
Requires-Dist: nanoleaf
